balldontlie/__init__.py
balldontlie/base.py
balldontlie/client.py
balldontlie/exceptions.py
balldontlie/epl/api.py
balldontlie/epl/models.py
balldontlie/mlb/api.py
balldontlie/mlb/models.py
balldontlie/nba/api.py
balldontlie/nba/models.py
balldontlie/nfl/api.py
balldontlie/nfl/models.py
balldontlie-0.1.5.dist-info/METADATA
balldontlie-0.1.5.dist-info/WHEEL
balldontlie-0.1.5.dist-info/top_level.txt
balldontlie-0.1.5.dist-info/RECORD
